Metadata-Version: 2.1
Name: titanic-ark
Version: 0.0.1
Summary: ฟังก์ชันของ Ark
Home-page: 
Author: ark
Author-email: wilcolnwza11@gmail.com
License: MIT
Keywords: titanic_ark
Classifier: Development Status :: 5 - Production/Stable
Classifier: Intended Audience :: Education
Classifier: Operating System :: Microsoft :: Windows :: Windows 11
Classifier: License :: OSI Approved :: MIT License
Classifier: Programming Language :: Python :: 3
License-File: LICENCE.txt
